{"name":"Verify Opened Chrome on Android","id":"test-app-basic-open-chrome;verify-opened-chrome-on-android","testSteps":[{"number":1,"description":"Given User goes to Menu","duration":4,"startTime":"2020-06-24T21:11:36.956356900+07:00[Asia/Bangkok]","result":"PENDING","precondition":false},{"number":2,"description":"And User clicks on Chrome","duration":0,"startTime":"2020-06-24T21:11:36.962339600+07:00[Asia/Bangkok]","result":"PENDING","precondition":false},{"number":3,"description":"Then Verify browser","duration":0,"startTime":"2020-06-24T21:11:36.963337600+07:00[Asia/Bangkok]","result":"PENDING","precondition":false}],"userStory":{"id":"test-app-basic-open-chrome","storyName":"Test App Basic open Chrome","path":"src/test/java/integration/resources/features/apptest.feature","type":"feature"},"featureTag":{"name":"Features/Test App Basic open Chrome","type":"feature"},"title":"Verify Opened Chrome on Android","startTime":"2020-06-24T21:11:36.647185300+07:00[Asia/Bangkok]","duration":346,"projectKey":"","annotatedResult":"PENDING","manual":false,"testSource":"Cucumber","result":"PENDING"}